qtmdi/__init__.py
qtmdi/__pyinstaller/__init__.py
qtmdi/__pyinstaller/hook-qtmdi.py
qtmdi/fonts/MaterialIcons-Regular-charmap.json
qtmdi/fonts/MaterialIcons-Regular.ttf
qtmdi/fonts/MaterialIconsOutlined-Regular-charmap.json
qtmdi/fonts/MaterialIconsOutlined-Regular.otf
qtmdi/fonts/MaterialIconsRound-Regular-charmap.json
qtmdi/fonts/MaterialIconsRound-Regular.otf
qtmdi/fonts/MaterialIconsSharp-Regular-charmap.json
qtmdi/fonts/MaterialIconsSharp-Regular.otf
qtmdi/fonts/MaterialIconsTwoTone-Regular-charmap.json
qtmdi/fonts/MaterialIconsTwoTone-Regular.otf
qtmdi/icons/charmap.json
qtmdi/icons/100/material-symbols-outlined.ttf
qtmdi/icons/100/material-symbols-rounded.ttf
qtmdi/icons/100/material-symbols-sharp.ttf
qtmdi/icons/200/material-symbols-outlined.ttf
qtmdi/icons/200/material-symbols-rounded.ttf
qtmdi/icons/200/material-symbols-sharp.ttf
qtmdi/icons/300/material-symbols-outlined.ttf
qtmdi/icons/300/material-symbols-rounded.ttf
qtmdi/icons/300/material-symbols-sharp.ttf
qtmdi/icons/400/material-symbols-outlined.ttf
qtmdi/icons/400/material-symbols-rounded.ttf
qtmdi/icons/400/material-symbols-sharp.ttf
qtmdi/icons/500/material-symbols-outlined.ttf
qtmdi/icons/500/material-symbols-rounded.ttf
qtmdi/icons/500/material-symbols-sharp.ttf
qtmdi/icons/600/material-symbols-outlined.ttf
qtmdi/icons/600/material-symbols-rounded.ttf
qtmdi/icons/600/material-symbols-sharp.ttf
qtmdi/icons/700/material-symbols-outlined.ttf
qtmdi/icons/700/material-symbols-rounded.ttf
qtmdi/icons/700/material-symbols-sharp.ttf
qtmdi/icons/base/material-symbols-outlined.ttf
qtmdi/icons/base/material-symbols-rounded.ttf
qtmdi/icons/base/material-symbols-sharp.ttf
qtmdi-1.1.53.dist-info/licenses/LICENSE
qtmdi-1.1.53.dist-info/METADATA
qtmdi-1.1.53.dist-info/WHEEL
qtmdi-1.1.53.dist-info/entry_points.txt
qtmdi-1.1.53.dist-info/top_level.txt
qtmdi-1.1.53.dist-info/RECORD
