Metadata-Version: 2.4
Name: QtMDi
Version: 1.1.53
Summary: QtMDI (Qt Material Design Icons)
Author-email: o-murphy <thehelixpg@gmail.com>
License: The MIT License
Project-URL: Homepage, https://github.com/o-murphy/QtMDi
Project-URL: Bug Reports, https://github.com/o-murphy/QtMDi/issues
Project-URL: Source, https://github.com/o-murphy/QtMDi
Keywords: pyqt,pyside,material-icons,material-symbols
Classifier: Intended Audience :: Developers
Classifier: Natural Language :: English
Classifier: Programming Language :: Python
Classifier: Topic :: Software Development :: Libraries :: Python Modules
Classifier: Programming Language :: Python :: 3
Classifier: Programming Language :: Python :: 3 :: Only
Classifier: Programming Language :: Python :: 3.8
Classifier: Programming Language :: Python :: 3.9
Classifier: Programming Language :: Python :: 3.10
Classifier: Programming Language :: Python :: 3.11
Classifier: Programming Language :: Python :: 3.12
Classifier: Operating System :: OS Independent
Classifier: Programming Language :: Python :: Implementation :: CPython
Requires-Python: >=3.8
License-File: LICENSE
Requires-Dist: qtawesome
Requires-Dist: qtpy
Provides-Extra: dev
Requires-Dist: pylint; extra == "dev"
Requires-Dist: flake8; extra == "dev"
Requires-Dist: pytest; extra == "dev"
Requires-Dist: bump2version; extra == "dev"
Dynamic: license-file
